[
  {
    "question": "In the anatomy of an Embedded Linux system, which component is responsible for initializing the DRAM controller before the kernel takes over?",
    "options": {
      "A": "Root File System",
      "B": "Bootloader",
      "C": "Device Tree",
      "D": "Kernel Space"
    },
    "answer": "B"
  },
  {
    "question": "What is the primary role of the 'zImage' or 'uImage' in an embedded system?",
    "options": {
      "A": "A compressed executable of the root filesystem",
      "B": "The compressed bootloader binary",
      "C": "The compressed Linux kernel image",
      "D": "A configuration file for hardware pins"
    },
    "answer": "C"
  },
  {
    "question": "Which of the following is a key difference between a Hard Real-Time OS and a Soft Real-Time OS?",
    "options": {
      "A": "Hard RTOS is faster than Soft RTOS",
      "B": "Hard RTOS guarantees completion within a deadline, while Soft RTOS prioritizes completion",
      "C": "Hard RTOS uses preemptive scheduling, while Soft RTOS only uses round-robin",
      "D": "Soft RTOS does not support multithreading"
    },
    "answer": "B"
  },
  {
    "question": "In Embedded Linux, what is the purpose of the Initrd (Initial RAM Disk)?",
    "options": {
      "A": "To store user application data permanently",
      "B": "To provide a temporary root file system until the real one is mounted",
      "C": "To manage CPU power states during boot",
      "D": "To act as a secondary bootloader"
    },
    "answer": "B"
  },
  {
    "question": "Which process state transition is valid when a process is waiting for an I/O operation to complete?",
    "options": {
      "A": "Running -> Ready",
      "B": "Ready -> Running",
      "C": "Running -> Blocked",
      "D": "Blocked -> Running"
    },
    "answer": "C"
  },
  {
    "question": "What happens to a process that terminates while its parent is still running but has not yet called wait()?",
    "options": {
      "A": "It becomes an Orphan process",
      "B": "It becomes a Zombie process",
      "C": "It is immediately deleted from the process table",
      "D": "The kernel sends a SIGKILL to the parent"
    },
    "answer": "B"
  },
  {
    "question": "Which POSIX function is used to set the attributes of a thread, such as its stack size, before creation?",
    "options": {
      "A": "pthread_create()",
      "B": "pthread_attr_init()",
      "C": "pthread_setstack()",
      "D": "pthread_join()"
    },
    "answer": "B"
  },
  {
    "question": "In IPC, which mechanism allows multiple processes to access the same physical memory pages directly?",
    "options": {
      "A": "Message Queues",
      "B": "Pipes",
      "C": "Shared Memory",
      "D": "Sockets"
    },
    "answer": "C"
  },
  {
    "question": "What is the primary disadvantage of using Shared Memory for IPC?",
    "options": {
      "A": "It is slower than Message Queues",
      "B": "It requires explicit synchronization (e.g., semaphores) to prevent race conditions",
      "C": "It can only be used between parent and child processes",
      "D": "The kernel copies data twice for every read/write"
    },
    "answer": "B"
  },
  {
    "question": "Which POSIX synchronization primitive is best suited for a 'one-to-many' notification signal?",
    "options": {
      "A": "Mutex",
      "B": "Binary Semaphore",
      "C": "Condition Variable",
      "D": "Spinlock"
    },
    "answer": "C"
  },
  {
    "question": "How does a Mutex differ from a Binary Semaphore in POSIX?",
    "options": {
      "A": "Mutexes support priority inheritance; semaphores generally do not",
      "B": "Semaphores have ownership; mutexes do not",
      "C": "Mutexes can be used for signaling; semaphores are only for locking",
      "D": "There is no difference"
    },
    "answer": "A"
  },
  {
    "question": "In Memory Management, what is 'Thrashing'?",
    "options": {
      "A": "A process being killed due to lack of memory",
      "B": "Excessive swapping of pages between RAM and disk, leading to low CPU utility",
      "C": "The fragmentation of the heap memory",
      "D": "The process of clearing the cache during a context switch"
    },
    "answer": "B"
  },
  {
    "question": "Which file system is specifically designed for Flash memory devices to handle wear leveling in Embedded Linux?",
    "options": {
      "A": "EXT4",
      "B": "FAT32",
      "C": "JFFS2",
      "D": "NFS"
    },
    "answer": "C"
  },
  {
    "question": "What is the purpose of the 'Virtual File System' (VFS) layer in Linux?",
    "options": {
      "A": "To create a RAM disk",
      "B": "To provide a uniform interface for different physical file systems",
      "C": "To encrypt files automatically",
      "D": "To manage virtual memory mapping"
    },
    "answer": "B"
  },
  {
    "question": "In POSIX threads, which function is used to ensure a thread waits for another to finish before continuing?",
    "options": {
      "A": "pthread_detach()",
      "B": "pthread_wait()",
      "C": "pthread_join()",
      "D": "pthread_yield()"
    },
    "answer": "C"
  },
  {
    "question": "What is Priority Inversion?",
    "options": {
      "A": "When a low-priority task is finished before a high-priority task starts",
      "B": "When a high-priority task is blocked by a low-priority task holding a required resource",
      "C": "When the scheduler fails to assign a priority to a process",
      "D": "When all processes are assigned the same priority level"
    },
    "answer": "B"
  },
  {
    "question": "Which POSIX primitive is used to synchronize a specific number of threads at a rendezvous point?",
    "options": {
      "A": "Mutex",
      "B": "Counting Semaphore",
      "C": "Barrier",
      "D": "Message Queue"
    },
    "answer": "C"
  },
  {
    "question": "What is the behavior of sem_post() in POSIX?",
    "options": {
      "A": "Decrements the semaphore value; blocks if value is 0",
      "B": "Increments the semaphore value and wakes up a blocked thread",
      "C": "Initializes a new semaphore",
      "D": "Deletes a semaphore from the system"
    },
    "answer": "B"
  },
  {
    "question": "In the context of the I/O subsystem, what is a 'Character Device'?",
    "options": {
      "A": "A device that handles data in large blocks (e.g., Hard Drive)",
      "B": "A device that handles data as a stream of bytes (e.g., Serial Port)",
      "C": "A device used only for text output",
      "D": "A virtual device used for process signaling"
    },
    "answer": "B"
  },
  {
    "question": "Which debugging tool allows you to trace system calls and signals made by a process in Linux?",
    "options": {
      "A": "GDB",
      "B": "Valgrind",
      "C": "strace",
      "D": "top"
    },
    "answer": "C"
  },
  {
    "question": "What is 'Internal Fragmentation' in memory management?",
    "options": {
      "A": "Unused memory space between allocated memory blocks",
      "B": "Unused memory within an allocated block of fixed size",
      "C": "The overhead of the page table",
      "D": "Memory leaked by a process"
    },
    "answer": "B"
  },
  {
    "question": "Which IPC mechanism is persistent even after the creating process has terminated (until explicitly deleted)?",
    "options": {
      "A": "Unnamed Pipes",
      "B": "Signals",
      "C": "POSIX Shared Memory (shm_open)",
      "D": "Local variables in a thread"
    },
    "answer": "C"
  },
  {
    "question": "In a condition variable, why must 'pthread_cond_wait' always be called inside a loop?",
    "options": {
      "A": "To handle spurious wakeups",
      "B": "To increase the priority of the thread",
      "C": "To prevent the mutex from being unlocked",
      "D": "To allow other threads to join"
    },
    "answer": "A"
  },
  {
    "question": "What is the primary function of the 'Translation Lookaside Buffer' (TLB)?",
    "options": {
      "A": "To store the entire page table",
      "B": "To cache recent virtual-to-physical address translations",
      "C": "To handle I/O interrupts",
      "D": "To synchronize data between CPU cores"
    },
    "answer": "B"
  },
  {
    "question": "Which of the following is a 'blocking' I/O operation?",
    "options": {
      "A": "Writing to a full buffer that returns immediately with an error",
      "B": "A read call that waits until data is available from a sensor",
      "C": "Asynchronous I/O where a callback is triggered later",
      "D": "Polling a status bit in a loop"
    },
    "answer": "B"
  },
  {
    "question": "What is the result of the 'fork()' system call in the child process?",
    "options": {
      "A": "It returns the PID of the parent",
      "B": "It returns 0",
      "C": "It returns a negative value",
      "D": "It returns the PID of the child"
    },
    "answer": "B"
  },
  {
    "question": "Which memory allocation strategy picks the smallest hole that is big enough to satisfy the request?",
    "options": {
      "A": "First Fit",
      "B": "Best Fit",
      "C": "Worst Fit",
      "D": "Next Fit"
    },
    "answer": "B"
  },
  {
    "question": "In POSIX, what is the default behavior of a Mutex when a thread tries to lock it a second time?",
    "options": {
      "A": "The call succeeds immediately",
      "B": "The call fails with an error",
      "C": "The thread deadlocks (blocks forever)",
      "D": "The mutex is automatically released"
    },
    "answer": "C"
  },
  {
    "question": "What does the 'Mounting' process do in an embedded system?",
    "options": {
      "A": "Attaches a physical file system to a specific directory in the VFS",
      "B": "Compiles the kernel code",
      "C": "Installs the bootloader into the MBR",
      "D": "Loads the application into RAM"
    },
    "answer": "A"
  },
  {
    "question": "Which debugging method involves using a hardware device to control the CPU and inspect registers?",
    "options": {
      "A": "Printk debugging",
      "B": "JTAG Debugging",
      "C": "Core dump analysis",
      "D": "Remote GDB via Serial"
    },
    "answer": "B"
  },
  {
    "question": "What is the purpose of 'Spinlocks' in a multi-core embedded system?",
    "options": {
      "A": "To put a thread to sleep until a resource is ready",
      "B": "To prevent a CPU from entering a low-power state",
      "C": "To wait for a short-duration lock without the overhead of a context switch",
      "D": "To manage the order of execution in a single-core system"
    },
    "answer": "C"
  },
  {
    "question": "Which segment of a process's memory contains uninitialized global variables?",
    "options": {
      "A": "Stack",
      "B": "Heap",
      "C": "Data Segment",
      "D": "BSS Segment"
    },
    "answer": "D"
  },
  {
    "question": "In Message Queues, what happens when a process tries to send a message to a full queue in default blocking mode?",
    "options": {
      "A": "The oldest message is overwritten",
      "B": "The message is silently dropped",
      "C": "The sending process is blocked until space is available",
      "D": "The queue is automatically resized"
    },
    "answer": "C"
  },
  {
    "question": "What is a 'Race Condition'?",
    "options": {
      "A": "When two processes run at the same speed",
      "B": "When the outcome of a process depends on the non-deterministic timing of other events",
      "C": "When a process finishes before its deadline",
      "D": "When the CPU clock speed is increased"
    },
    "answer": "B"
  },
  {
    "question": "Which of the following is NOT a requirement for a Deadlock to occur?",
    "options": {
      "A": "Mutual Exclusion",
      "B": "Hold and Wait",
      "C": "No Preemption",
      "D": "Priority Inheritance"
    },
    "answer": "D"
  },
  {
    "question": "In Linux, which signal is sent to a process when it accesses an invalid memory address?",
    "options": {
      "A": "SIGINT",
      "B": "SIGSEGV",
      "C": "SIGKILL",
      "D": "SIGSTOP"
    },
    "answer": "B"
  },
  {
    "question": "What is the function of the Scheduler in an OS?",
    "options": {
      "A": "To allocate memory to new processes",
      "B": "To decide which process in the ready queue should run next on the CPU",
      "C": "To manage the hardware interrupts",
      "D": "To translate file names into disk sectors"
    },
    "answer": "B"
  },
  {
    "question": "Which POSIX function is used to delete a named semaphore?",
    "options": {
      "A": "sem_close()",
      "B": "sem_destroy()",
      "C": "sem_unlink()",
      "D": "sem_wait()"
    },
    "answer": "C"
  },
  {
    "question": "What is a 'Context Switch'?",
    "options": {
      "A": "Switching between User mode and Kernel mode only",
      "B": "Saving the state of a current process and loading the state of the next process",
      "C": "Moving a file from one directory to another",
      "D": "Changing the priority of a process"
    },
    "answer": "B"
  },
  {
    "question": "What is the primary benefit of 'Demand Paging'?",
    "options": {
      "A": "It makes the system run faster",
      "B": "It allows programs larger than physical memory to be executed",
      "C": "It prevents all types of fragmentation",
      "D": "It eliminates the need for a MMU"
    },
    "answer": "B"
  },
  {
    "question": "In Linux, which directory contains virtual files that represent kernel and process information?",
    "options": {
      "A": "/bin",
      "B": "/proc",
      "C": "/usr",
      "D": "/etc"
    },
    "answer": "B"
  },
  {
    "question": "Which of the following is true about 'Threads' compared to 'Processes'?",
    "options": {
      "A": "Threads have their own independent address space",
      "B": "Context switching between threads is generally faster than between processes",
      "C": "Threads cannot share global variables",
      "D": "A thread failure never affects other threads in the same process"
    },
    "answer": "B"
  },
  {
    "question": "What is the 'Working Set' of a process?",
    "options": {
      "A": "The total number of files it has open",
      "B": "The set of pages currently in the CPU cache",
      "C": "The set of pages a process is actively using during a time interval",
      "D": "The total size of the process binary on disk"
    },
    "answer": "C"
  },
  {
    "question": "In POSIX Message Queues, how is the 'mq_open' function used differently from a standard 'open'?",
    "options": {
      "A": "It creates a file on the physical disk",
      "B": "It uses a name starting with a '/' but operates in a virtual namespace",
      "C": "It can only be used by the root user",
      "D": "It returns a file pointer (FILE*) instead of a descriptor"
    },
    "answer": "B"
  },
  {
    "question": "Which component of an Embedded Linux system contains the system configuration files (e.g., startup scripts)?",
    "options": {
      "A": "Kernel Image",
      "B": "Bootloader Environment",
      "C": "/etc directory in the Root File System",
      "D": "Process Control Block"
    },
    "answer": "C"
  },
  {
    "question": "What does 'Preemption' mean in the context of an OS scheduler?",
    "options": {
      "A": "A process voluntarily gives up the CPU",
      "B": "The OS forcibly removes a running process to give the CPU to another",
      "C": "A process finishes its execution normally",
      "D": "The CPU enters a sleep state"
    },
    "answer": "B"
  },
  {
    "question": "Which command is used in GDB to execute the next line of code, stepping into functions?",
    "options": {
      "A": "next",
      "B": "step",
      "C": "continue",
      "D": "finish"
    },
    "answer": "B"
  },
  {
    "question": "What is the main advantage of using a 'Barrier' synchronization?",
    "options": {
      "A": "It prevents more than one thread from entering a critical section",
      "B": "It ensures that no thread proceeds until all participating threads have reached the same point",
      "C": "It allows for faster memory access",
      "D": "It automatically resolves priority inversion"
    },
    "answer": "B"
  },
  {
    "question": "In the context of Shared Memory, what does 'shm_unlink' do?",
    "options": {
      "A": "It detaches the memory from the current process",
      "B": "It marks the shared memory object for removal once all processes close it",
      "C": "It synchronizes the memory with the disk",
      "D": "It changes the permissions of the memory segment"
    },
    "answer": "B"
  },
  {
    "question": "Which of the following describes 'Direct Memory Access' (DMA)?",
    "options": {
      "A": "The CPU directly accessing the hardware registers",
      "B": "A hardware feature allowing I/O devices to transfer data to/from memory without CPU involvement",
      "C": "A process accessing another process's memory",
      "D": "The bootloader loading the kernel into RAM"
    },
    "answer": "B"
  }
]